{"access_point":{"height":48,"pixelRatio":2,"width":48,"x":128,"y":64},"access_point-minor":{"height":36,"pixelRatio":2,"width":36,"x":320,"y":214},"access_point-noaccess":{"height":48,"pixelRatio":2,"width":48,"x":128,"y":112},"arrow-left":{"height":30,"pixelRatio":2,"width":46,"x":356,"y":190},"arrow-right":{"height":30,"pixelRatio":2,"width":46,"x":402,"y":204},"arrows-leftright":{"height":30,"pixelRatio":2,"width":66,"x":320,"y":96},"beaver_dam":{"height":46,"pixelRatio":2,"width":42,"x":386,"y":96},"beaver_dam-canoeable":{"height":48,"pixelRatio":2,"width":48,"x":128,"y":160},"beaver_dam-hazard":{"height":48,"pixelRatio":2,"width":48,"x":128,"y":208},"bird_refuge":{"height":64,"pixelRatio":2,"width":64,"x":0,"y":0},"bison_refuge":{"height":64,"pixelRatio":2,"width":64,"x":0,"y":64},"cairn":{"height":48,"pixelRatio":2,"width":36,"x":428,"y":96},"campground":{"height":48,"pixelRatio":2,"width":48,"x":176,"y":64},"campground-noaccess":{"height":48,"pixelRatio":2,"width":48,"x":192,"y":0},"campsite":{"height":40,"pixelRatio":2,"width":48,"x":320,"y":126},"caravan_site":{"height":48,"pixelRatio":2,"width":48,"x":176,"y":112},"caravan_site-noaccess":{"height":48,"pixelRatio":2,"width":48,"x":176,"y":160},"dam":{"height":36,"pixelRatio":2,"width":36,"x":356,"y":220},"dam-canoeable":{"height":48,"pixelRatio":2,"width":48,"x":176,"y":208},"dam-hazard":{"height":48,"pixelRatio":2,"width":48,"x":224,"y":48},"disallowed-stripes":{"height":12,"pixelRatio":2,"width":14,"x":368,"y":126},"ferry":{"height":48,"pixelRatio":2,"width":48,"x":240,"y":0},"ferry-noaccess":{"height":48,"pixelRatio":2,"width":48,"x":224,"y":96},"forest_reserve":{"height":64,"pixelRatio":2,"width":64,"x":0,"y":128},"game_land":{"height":64,"pixelRatio":2,"width":64,"x":0,"y":192},"guidepost":{"height":48,"pixelRatio":2,"width":36,"x":368,"y":142},"lean_to":{"height":40,"pixelRatio":2,"width":36,"x":404,"y":144},"lock":{"height":46,"pixelRatio":2,"width":28,"x":480,"y":0},"lock-canoeable":{"height":48,"pixelRatio":2,"width":48,"x":224,"y":144},"lock-hazard":{"height":48,"pixelRatio":2,"width":48,"x":224,"y":192},"nature_reserve":{"height":64,"pixelRatio":2,"width":64,"x":64,"y":0},"park":{"height":64,"pixelRatio":2,"width":64,"x":64,"y":64},"peak":{"height":36,"pixelRatio":2,"width":44,"x":464,"y":136},"protected_area":{"height":64,"pixelRatio":2,"width":64,"x":64,"y":128},"question":{"height":48,"pixelRatio":2,"width":48,"x":272,"y":48},"ranger_station":{"height":48,"pixelRatio":2,"width":48,"x":288,"y":0},"ranger_station-noaccess":{"height":48,"pixelRatio":2,"width":48,"x":272,"y":96},"restricted-zone":{"height":8,"pixelRatio":2,"width":8,"x":356,"y":166},"route_marker":{"height":48,"pixelRatio":2,"width":36,"x":320,"y":166},"slipway-canoe":{"height":48,"pixelRatio":2,"width":48,"x":272,"y":144},"slipway-canoe-noaccess":{"height":48,"pixelRatio":2,"width":48,"x":272,"y":192},"slipway-canoe-trailer":{"height":48,"pixelRatio":2,"width":48,"x":320,"y":48},"slipway-canoe-trailer-noaccess":{"height":48,"pixelRatio":2,"width":48,"x":336,"y":0},"streamgage":{"height":48,"pixelRatio":2,"width":48,"x":368,"y":48},"trailhead":{"height":48,"pixelRatio":2,"width":48,"x":384,"y":0},"trailhead-noaccess":{"height":48,"pixelRatio":2,"width":48,"x":416,"y":48},"viewpoint":{"height":32,"pixelRatio":2,"width":44,"x":440,"y":172},"waterfall":{"height":40,"pixelRatio":2,"width":40,"x":464,"y":96},"waterfall-canoeable":{"height":48,"pixelRatio":2,"width":48,"x":432,"y":0},"waterfall-hazard":{"height":48,"pixelRatio":2,"width":48,"x":464,"y":48},"wilderness_preserve":{"height":64,"pixelRatio":2,"width":64,"x":64,"y":192},"wildlife_refuge":{"height":64,"pixelRatio":2,"width":64,"x":128,"y":0}}